napari_allencell_annotator/__init__.py
napari_allencell_annotator/_dock_widget.py
napari_allencell_annotator/_style.py
napari_allencell_annotator/app.py
napari_allencell_annotator/_tests/__init__.py
napari_allencell_annotator/_tests/popup_test.py
napari_allencell_annotator/_tests/style_test.py
napari_allencell_annotator/_tests/fakes/__init__.py
napari_allencell_annotator/_tests/fakes/fake_viewer.py
napari_allencell_annotator/_tests/utils/__init__.py
napari_allencell_annotator/_tests/utils/test_file_utils.py
napari_allencell_annotator/_tests/utils/test_image_utils.py
napari_allencell_annotator/constants/__init__.py
napari_allencell_annotator/constants/constants.py
napari_allencell_annotator/controller/__init__.py
napari_allencell_annotator/controller/annotator_controller.py
napari_allencell_annotator/model/__init__.py
napari_allencell_annotator/model/annotation_model.py
napari_allencell_annotator/model/combo_key.py
napari_allencell_annotator/model/images_model.py
napari_allencell_annotator/model/key.py
napari_allencell_annotator/styles/main.qss
napari_allencell_annotator/util/__init__.py
napari_allencell_annotator/util/directories.py
napari_allencell_annotator/util/file_utils.py
napari_allencell_annotator/util/image_utils.py
napari_allencell_annotator/util/json_utils.py
napari_allencell_annotator/view/__init__.py
napari_allencell_annotator/view/annotator_view.py
napari_allencell_annotator/view/i_viewer.py
napari_allencell_annotator/view/images_view.py
napari_allencell_annotator/view/main_view.py
napari_allencell_annotator/view/viewer.py
napari_allencell_annotator/widgets/__init__.py
napari_allencell_annotator/widgets/annotation_item.py
napari_allencell_annotator/widgets/annotation_widget.py
napari_allencell_annotator/widgets/create_dialog.py
napari_allencell_annotator/widgets/file_input.py
napari_allencell_annotator/widgets/file_item.py
napari_allencell_annotator/widgets/file_scrollable_popup.py
napari_allencell_annotator/widgets/files_widget.py
napari_allencell_annotator-2.0.1.dist-info/LICENSE
napari_allencell_annotator-2.0.1.dist-info/METADATA
napari_allencell_annotator-2.0.1.dist-info/WHEEL
napari_allencell_annotator-2.0.1.dist-info/entry_points.txt
napari_allencell_annotator-2.0.1.dist-info/top_level.txt
napari_allencell_annotator-2.0.1.dist-info/RECORD
