Metadata-Version: 2.1
Name: napari-allencell-annotator
Version: 2.0.1
Summary: A plugin that enables annotations provided by Allen Institute for Cell Science
Home-page: https://github.com/aics-int/napari-allencell-annotator/
Author: Allen Institute for Cell Science
Classifier: Intended Audience :: Science/Research
Classifier: Framework :: napari
Classifier: Topic :: Scientific/Engineering
Classifier: Topic :: Scientific/Engineering :: Visualization
Classifier: Topic :: Scientific/Engineering :: Information Analysis
Classifier: Programming Language :: Python :: 3.9
Classifier: Programming Language :: Python :: 3.10
Classifier: Operating System :: OS Independent
Classifier: License :: OSI Approved :: BSD License
Requires-Python: >=3.9
License-File: LICENSE
Requires-Dist: napari >=0.4.9
Requires-Dist: napari-plugin-engine >=0.1.4
Requires-Dist: numpy
Requires-Dist: xarray >=2022.6.0
Requires-Dist: magicgui >=0.3.7
Requires-Dist: aicspylibczi >=3.0.5
Requires-Dist: fsspec >=2022.8.2
Requires-Dist: bioformats-jar
Requires-Dist: bfio
Requires-Dist: qtpy
Requires-Dist: bioio
Requires-Dist: bioio-ome-tiff
Requires-Dist: bioio-czi
Requires-Dist: bioio-ome-zarr
Requires-Dist: tifffile >=2021.8.30
Requires-Dist: bioio-imageio
Provides-Extra: all
Requires-Dist: napari >=0.4.9 ; extra == 'all'
Requires-Dist: napari-plugin-engine >=0.1.4 ; extra == 'all'
Requires-Dist: numpy ; extra == 'all'
Requires-Dist: xarray >=2022.6.0 ; extra == 'all'
Requires-Dist: magicgui >=0.3.7 ; extra == 'all'
Requires-Dist: aicspylibczi >=3.0.5 ; extra == 'all'
Requires-Dist: fsspec >=2022.8.2 ; extra == 'all'
Requires-Dist: bioformats-jar ; extra == 'all'
Requires-Dist: bfio ; extra == 'all'
Requires-Dist: qtpy ; extra == 'all'
Requires-Dist: bioio ; extra == 'all'
Requires-Dist: bioio-ome-tiff ; extra == 'all'
Requires-Dist: bioio-czi ; extra == 'all'
Requires-Dist: bioio-ome-zarr ; extra == 'all'
Requires-Dist: tifffile >=2021.8.30 ; extra == 'all'
Requires-Dist: bioio-imageio ; extra == 'all'
Requires-Dist: black >=19.10b0 ; extra == 'all'
Requires-Dist: codecov >=2.0.22 ; extra == 'all'
Requires-Dist: docutils <0.16,>=0.10 ; extra == 'all'
Requires-Dist: flake8 >=3.7.7 ; extra == 'all'
Requires-Dist: psutil >=5.7.0 ; extra == 'all'
Requires-Dist: pytest >=4.3.0 ; extra == 'all'
Requires-Dist: pytest-cov ==2.6.1 ; extra == 'all'
Requires-Dist: pytest-raises >=0.10 ; extra == 'all'
Requires-Dist: pytest-qt >=3.3.0 ; extra == 'all'
Requires-Dist: quilt3 >=3.1.12 ; extra == 'all'
Requires-Dist: pyqt5 ; extra == 'all'
Requires-Dist: pytest-runner ; extra == 'all'
Requires-Dist: bumpversion >=0.5.3 ; extra == 'all'
Requires-Dist: gitchangelog >=3.0.4 ; extra == 'all'
Requires-Dist: ipython >=7.5.0 ; extra == 'all'
Requires-Dist: m2r >=0.2.1 ; extra == 'all'
Requires-Dist: pytest-runner >=4.4 ; extra == 'all'
Requires-Dist: Sphinx <3,>=2.0.0b1 ; extra == 'all'
Requires-Dist: sphinx-rtd-theme >=0.1.2 ; extra == 'all'
Requires-Dist: tox >=3.5.2 ; extra == 'all'
Requires-Dist: twine >=1.13.0 ; extra == 'all'
Requires-Dist: wheel >=0.33.1 ; extra == 'all'
Provides-Extra: dev
Requires-Dist: black >=19.10b0 ; extra == 'dev'
Requires-Dist: bumpversion >=0.5.3 ; extra == 'dev'
Requires-Dist: docutils <0.16,>=0.10 ; extra == 'dev'
Requires-Dist: flake8 >=3.7.7 ; extra == 'dev'
Requires-Dist: gitchangelog >=3.0.4 ; extra == 'dev'
Requires-Dist: ipython >=7.5.0 ; extra == 'dev'
Requires-Dist: m2r >=0.2.1 ; extra == 'dev'
Requires-Dist: pytest >=4.3.0 ; extra == 'dev'
Requires-Dist: pytest-cov ==2.6.1 ; extra == 'dev'
Requires-Dist: pytest-raises >=0.10 ; extra == 'dev'
Requires-Dist: pytest-runner >=4.4 ; extra == 'dev'
Requires-Dist: pytest-qt >=3.3.0 ; extra == 'dev'
Requires-Dist: quilt3 >=3.1.12 ; extra == 'dev'
Requires-Dist: Sphinx <3,>=2.0.0b1 ; extra == 'dev'
Requires-Dist: sphinx-rtd-theme >=0.1.2 ; extra == 'dev'
Requires-Dist: tox >=3.5.2 ; extra == 'dev'
Requires-Dist: twine >=1.13.0 ; extra == 'dev'
Requires-Dist: wheel >=0.33.1 ; extra == 'dev'
Provides-Extra: setup
Requires-Dist: pytest-runner ; extra == 'setup'
Provides-Extra: test
Requires-Dist: black >=19.10b0 ; extra == 'test'
Requires-Dist: codecov >=2.0.22 ; extra == 'test'
Requires-Dist: docutils <0.16,>=0.10 ; extra == 'test'
Requires-Dist: flake8 >=3.7.7 ; extra == 'test'
Requires-Dist: psutil >=5.7.0 ; extra == 'test'
Requires-Dist: pytest >=4.3.0 ; extra == 'test'
Requires-Dist: pytest-cov ==2.6.1 ; extra == 'test'
Requires-Dist: pytest-raises >=0.10 ; extra == 'test'
Requires-Dist: pytest-qt >=3.3.0 ; extra == 'test'
Requires-Dist: quilt3 >=3.1.12 ; extra == 'test'
Requires-Dist: pyqt5 ; extra == 'test'
